ruminant/__main__.py
ruminant/buf.py
ruminant/constants.py
ruminant/gui.py
ruminant/main.py
ruminant/module.py
ruminant/oids-tool.py
ruminant/oids.py
ruminant/oids.txt
ruminant/test_core.py
ruminant/tests.py
ruminant/utils.py
ruminant/modules/__init__.py
ruminant/modules/android.py
ruminant/modules/audio.py
ruminant/modules/compression.py
ruminant/modules/containers.py
ruminant/modules/crypto.py
ruminant/modules/documents.py
ruminant/modules/fonts.py
ruminant/modules/images.py
ruminant/modules/misc.py
ruminant/modules/text.py
ruminant/modules/videos.py
ruminant/thirdparty/lzw.py
ruminant/thirdparty/png.py
ruminant-0.0.30.dist-info/licenses/LICENSE
ruminant-0.0.30.dist-info/METADATA
ruminant-0.0.30.dist-info/WHEEL
ruminant-0.0.30.dist-info/entry_points.txt
ruminant-0.0.30.dist-info/top_level.txt
ruminant-0.0.30.dist-info/RECORD
