Metadata-Version: 2.4
Name: ruminant
Version: 0.0.30
Summary: Recursive metadata extraction tool
Author: Laura Kirsch
License-Expression: LGPL-3.0
Project-URL: Homepage, https://github.com/jakiki6/ruminant
Project-URL: Issues, https://github.com/jakiki6/ruminant/issues
Classifier: Programming Language :: Python :: 3
Classifier: Operating System :: OS Independent
Requires-Python: >=3.10
License-File: LICENSE
Provides-Extra: recommended
Requires-Dist: tqdm; extra == "recommended"
Requires-Dist: pyzstd; extra == "recommended"
Requires-Dist: backports.zstd; extra == "recommended"
Provides-Extra: dev
Requires-Dist: flake8; extra == "dev"
Dynamic: license-file
